{
  "Name":           "spring-data-redis",
  "Title":          "Spring Data Redis",
  "SourceUrl":      "http://central.maven.org/maven2/org/springframework/data/spring-data-redis/",
  "Maintainer":     "Andrey P.",
  "MaintainerUrl":  "http://abi-laboratory.pro/",

  "Versions": [
  {
    "Number":         "1.8.6",
    "Installed":      "src/spring-data-redis/1.8.6",
    "Source":         "src/spring-data-redis/1.8.6/spring-data-redis-1.8.6.RELEASE.jar",
    "Changelog":      "Off",
    "PkgDiff":        "Off"
  },
  {
    "Number":         "1.8.5",
    "Installed":      "src/spring-data-redis/1.8.5",
    "Source":         "src/spring-data-redis/1.8.5/spring-data-redis-1.8.5.RELEASE.jar",
    "Changelog":      "Off",
    "PkgDiff":        "Off"
  },
  {
    "Number":         "1.8.4",
    "Installed":      "src/spring-data-redis/1.8.4",
    "Source":         "src/spring-data-redis/1.8.4/spring-data-redis-1.8.4.RELEASE.jar",
    "Changelog":      "Off",
    "PkgDiff":        "Off"
  },
  {
    "Number":         "1.8.3",
    "Installed":      "src/spring-data-redis/1.8.3",
    "Source":         "src/spring-data-redis/1.8.3/spring-data-redis-1.8.3.RELEASE.jar",
    "Changelog":      "Off",
    "PkgDiff":        "Off"
  },
  {
    "Number":         "1.8.2",
    "Installed":      "src/spring-data-redis/1.8.2",
    "Source":         "src/spring-data-redis/1.8.2/spring-data-redis-1.8.2.RELEASE.jar",
    "Changelog":      "Off",
    "PkgDiff":        "Off"
  },
  {
    "Number":         "1.8.1",
    "Installed":      "src/spring-data-redis/1.8.1",
    "Source":         "src/spring-data-redis/1.8.1/spring-data-redis-1.8.1.RELEASE.jar",
    "Changelog":      "Off",
    "PkgDiff":        "Off"
  },
  {
    "Number":         "1.8.0",
    "Installed":      "src/spring-data-redis/1.8.0",
    "Source":         "src/spring-data-redis/1.8.0/spring-data-redis-1.8.0.RELEASE.jar",
    "Changelog":      "Off",
    "PkgDiff":        "Off"
  },
  {
    "Number":         "1.7.11",
    "Installed":      "src/spring-data-redis/1.7.11",
    "Source":         "src/spring-data-redis/1.7.11/spring-data-redis-1.7.11.RELEASE.jar",
    "Changelog":      "Off",
    "PkgDiff":        "Off"
  },
  {
    "Number":         "1.7.10",
    "Installed":      "src/spring-data-redis/1.7.10",
    "Source":         "src/spring-data-redis/1.7.10/spring-data-redis-1.7.10.RELEASE.jar",
    "Changelog":      "Off",
    "PkgDiff":        "Off"
  },
  {
    "Number":         "1.7.9",
    "Installed":      "src/spring-data-redis/1.7.9",
    "Source":         "src/spring-data-redis/1.7.9/spring-data-redis-1.7.9.RELEASE.jar",
    "Changelog":      "Off",
    "PkgDiff":        "Off"
  },
  {
    "Number":         "1.7.8",
    "Installed":      "src/spring-data-redis/1.7.8",
    "Source":         "src/spring-data-redis/1.7.8/spring-data-redis-1.7.8.RELEASE.jar",
    "Changelog":      "Off",
    "PkgDiff":        "Off"
  },
  {
    "Number":         "1.7.7",
    "Installed":      "src/spring-data-redis/1.7.7",
    "Source":         "src/spring-data-redis/1.7.7/spring-data-redis-1.7.7.RELEASE.jar",
    "Changelog":      "Off",
    "PkgDiff":        "Off"
  },
  {
    "Number":         "1.7.6",
    "Installed":      "src/spring-data-redis/1.7.6",
    "Source":         "src/spring-data-redis/1.7.6/spring-data-redis-1.7.6.RELEASE.jar",
    "Changelog":      "Off",
    "PkgDiff":        "Off"
  },
  {
    "Number":         "1.7.5",
    "Installed":      "src/spring-data-redis/1.7.5",
    "Source":         "src/spring-data-redis/1.7.5/spring-data-redis-1.7.5.RELEASE.jar",
    "Changelog":      "Off",
    "PkgDiff":        "Off"
  },
  {
    "Number":         "1.7.4",
    "Installed":      "src/spring-data-redis/1.7.4",
    "Source":         "src/spring-data-redis/1.7.4/spring-data-redis-1.7.4.RELEASE.jar",
    "Changelog":      "Off",
    "PkgDiff":        "Off"
  },
  {
    "Number":         "1.7.3",
    "Installed":      "src/spring-data-redis/1.7.3",
    "Source":         "src/spring-data-redis/1.7.3/spring-data-redis-1.7.3.RELEASE.jar",
    "Changelog":      "Off",
    "PkgDiff":        "Off"
  },
  {
    "Number":         "1.7.2",
    "Installed":      "src/spring-data-redis/1.7.2",
    "Source":         "src/spring-data-redis/1.7.2/spring-data-redis-1.7.2.RELEASE.jar",
    "Changelog":      "Off",
    "PkgDiff":        "Off"
  },
  {
    "Number":         "1.7.1",
    "Installed":      "src/spring-data-redis/1.7.1",
    "Source":         "src/spring-data-redis/1.7.1/spring-data-redis-1.7.1.RELEASE.jar",
    "Changelog":      "Off",
    "PkgDiff":        "Off"
  },
  {
    "Number":         "1.7.0",
    "Installed":      "src/spring-data-redis/1.7.0",
    "Source":         "src/spring-data-redis/1.7.0/spring-data-redis-1.7.0.RELEASE.jar",
    "Changelog":      "Off",
    "PkgDiff":        "Off"
  },
  {
    "Number":         "1.6.6",
    "Installed":      "src/spring-data-redis/1.6.6",
    "Source":         "src/spring-data-redis/1.6.6/spring-data-redis-1.6.6.RELEASE.jar",
    "Changelog":      "Off",
    "PkgDiff":        "Off"
  },
  {
    "Number":         "1.6.5",
    "Installed":      "src/spring-data-redis/1.6.5",
    "Source":         "src/spring-data-redis/1.6.5/spring-data-redis-1.6.5.RELEASE.jar",
    "Changelog":      "Off",
    "PkgDiff":        "Off"
  },
  {
    "Number":         "1.6.4",
    "Installed":      "src/spring-data-redis/1.6.4",
    "Source":         "src/spring-data-redis/1.6.4/spring-data-redis-1.6.4.RELEASE.jar",
    "Changelog":      "Off",
    "PkgDiff":        "Off"
  },
  {
    "Number":         "1.6.2",
    "Installed":      "src/spring-data-redis/1.6.2",
    "Source":         "src/spring-data-redis/1.6.2/spring-data-redis-1.6.2.RELEASE.jar",
    "Changelog":      "Off",
    "PkgDiff":        "Off"
  },
  {
    "Number":         "1.6.1",
    "Installed":      "src/spring-data-redis/1.6.1",
    "Source":         "src/spring-data-redis/1.6.1/spring-data-redis-1.6.1.RELEASE.jar",
    "Changelog":      "Off",
    "PkgDiff":        "Off"
  },
  {
    "Number":         "1.6.0",
    "Installed":      "src/spring-data-redis/1.6.0",
    "Source":         "src/spring-data-redis/1.6.0/spring-data-redis-1.6.0.RELEASE.jar",
    "Changelog":      "Off",
    "PkgDiff":        "Off"
  },
  {
    "Number":         "1.5.2",
    "Installed":      "src/spring-data-redis/1.5.2",
    "Source":         "src/spring-data-redis/1.5.2/spring-data-redis-1.5.2.RELEASE.jar",
    "Changelog":      "Off",
    "PkgDiff":        "Off"
  },
  {
    "Number":         "1.5.1",
    "Installed":      "src/spring-data-redis/1.5.1",
    "Source":         "src/spring-data-redis/1.5.1/spring-data-redis-1.5.1.RELEASE.jar",
    "Changelog":      "Off",
    "PkgDiff":        "Off"
  },
  {
    "Number":         "1.5.0",
    "Installed":      "src/spring-data-redis/1.5.0",
    "Source":         "src/spring-data-redis/1.5.0/spring-data-redis-1.5.0.RELEASE.jar",
    "Changelog":      "Off",
    "PkgDiff":        "Off"
  },
  {
    "Number":         "1.4.4",
    "Installed":      "src/spring-data-redis/1.4.4",
    "Source":         "src/spring-data-redis/1.4.4/spring-data-redis-1.4.4.RELEASE.jar",
    "Changelog":      "Off",
    "PkgDiff":        "Off"
  },
  {
    "Number":         "1.4.3",
    "Installed":      "src/spring-data-redis/1.4.3",
    "Source":         "src/spring-data-redis/1.4.3/spring-data-redis-1.4.3.RELEASE.jar",
    "Changelog":      "Off",
    "PkgDiff":        "Off"
  },
  {
    "Number":         "1.4.2",
    "Installed":      "src/spring-data-redis/1.4.2",
    "Source":         "src/spring-data-redis/1.4.2/spring-data-redis-1.4.2.RELEASE.jar",
    "Changelog":      "Off",
    "PkgDiff":        "Off"
  },
  {
    "Number":         "1.4.1",
    "Installed":      "src/spring-data-redis/1.4.1",
    "Source":         "src/spring-data-redis/1.4.1/spring-data-redis-1.4.1.RELEASE.jar",
    "Changelog":      "Off",
    "PkgDiff":        "Off"
  },
  {
    "Number":         "1.4.0",
    "Installed":      "src/spring-data-redis/1.4.0",
    "Source":         "src/spring-data-redis/1.4.0/spring-data-redis-1.4.0.RELEASE.jar",
    "Changelog":      "Off",
    "PkgDiff":        "Off"
  },
  {
    "Number":         "1.3.6",
    "Installed":      "src/spring-data-redis/1.3.6",
    "Source":         "src/spring-data-redis/1.3.6/spring-data-redis-1.3.6.RELEASE.jar",
    "Changelog":      "Off",
    "PkgDiff":        "Off"
  },
  {
    "Number":         "1.3.5",
    "Installed":      "src/spring-data-redis/1.3.5",
    "Source":         "src/spring-data-redis/1.3.5/spring-data-redis-1.3.5.RELEASE.jar",
    "Changelog":      "Off",
    "PkgDiff":        "Off"
  },
  {
    "Number":         "1.3.4",
    "Installed":      "src/spring-data-redis/1.3.4",
    "Source":         "src/spring-data-redis/1.3.4/spring-data-redis-1.3.4.RELEASE.jar",
    "Changelog":      "Off",
    "PkgDiff":        "Off"
  },
  {
    "Number":         "1.3.2",
    "Installed":      "src/spring-data-redis/1.3.2",
    "Source":         "src/spring-data-redis/1.3.2/spring-data-redis-1.3.2.RELEASE.jar",
    "Changelog":      "Off",
    "PkgDiff":        "Off"
  },
  {
    "Number":         "1.3.1",
    "Installed":      "src/spring-data-redis/1.3.1",
    "Source":         "src/spring-data-redis/1.3.1/spring-data-redis-1.3.1.RELEASE.jar",
    "Changelog":      "Off",
    "PkgDiff":        "Off"
  },
  {
    "Number":         "1.3.0",
    "Installed":      "src/spring-data-redis/1.3.0",
    "Source":         "src/spring-data-redis/1.3.0/spring-data-redis-1.3.0.RELEASE.jar",
    "Changelog":      "Off",
    "PkgDiff":        "Off"
  },
  {
    "Number":         "1.2.1",
    "Installed":      "src/spring-data-redis/1.2.1",
    "Source":         "src/spring-data-redis/1.2.1/spring-data-redis-1.2.1.RELEASE.jar",
    "Changelog":      "Off",
    "PkgDiff":        "Off"
  },
  {
    "Number":         "1.2.0",
    "Installed":      "src/spring-data-redis/1.2.0",
    "Source":         "src/spring-data-redis/1.2.0/spring-data-redis-1.2.0.RELEASE.jar",
    "Changelog":      "Off",
    "PkgDiff":        "Off"
  },
  {
    "Number":         "1.1.1",
    "Installed":      "src/spring-data-redis/1.1.1",
    "Source":         "src/spring-data-redis/1.1.1/spring-data-redis-1.1.1.RELEASE.jar",
    "Changelog":      "Off",
    "PkgDiff":        "Off"
  },
  {
    "Number":         "1.1.0",
    "Installed":      "src/spring-data-redis/1.1.0",
    "Source":         "src/spring-data-redis/1.1.0/spring-data-redis-1.1.0.RELEASE.jar",
    "Changelog":      "Off",
    "PkgDiff":        "Off"
  },
  {
    "Number":         "1.0.6",
    "Installed":      "src/spring-data-redis/1.0.6",
    "Source":         "src/spring-data-redis/1.0.6/spring-data-redis-1.0.6.RELEASE.jar",
    "Changelog":      "Off",
    "PkgDiff":        "Off"
  },
  {
    "Number":         "1.0.5",
    "Installed":      "src/spring-data-redis/1.0.5",
    "Source":         "src/spring-data-redis/1.0.5/spring-data-redis-1.0.5.RELEASE.jar",
    "Changelog":      "Off",
    "PkgDiff":        "Off"
  },
  {
    "Number":         "1.0.4",
    "Installed":      "src/spring-data-redis/1.0.4",
    "Source":         "src/spring-data-redis/1.0.4/spring-data-redis-1.0.4.RELEASE.jar",
    "Changelog":      "Off",
    "PkgDiff":        "Off"
  },
  {
    "Number":         "1.0.3",
    "Installed":      "src/spring-data-redis/1.0.3",
    "Source":         "src/spring-data-redis/1.0.3/spring-data-redis-1.0.3.RELEASE.jar",
    "Changelog":      "Off",
    "PkgDiff":        "Off"
  },
  {
    "Number":         "1.0.2",
    "Installed":      "src/spring-data-redis/1.0.2",
    "Source":         "src/spring-data-redis/1.0.2/spring-data-redis-1.0.2.RELEASE.jar",
    "Changelog":      "Off",
    "PkgDiff":        "Off"
  },
  {
    "Number":         "1.0.1",
    "Installed":      "src/spring-data-redis/1.0.1",
    "Source":         "src/spring-data-redis/1.0.1/spring-data-redis-1.0.1.RELEASE.jar",
    "Changelog":      "Off",
    "PkgDiff":        "Off"
  },
  {
    "Number":         "1.0.0",
    "Installed":      "src/spring-data-redis/1.0.0",
    "Source":         "src/spring-data-redis/1.0.0/spring-data-redis-1.0.0.RELEASE.jar",
    "Changelog":      "Off",
    "PkgDiff":        "Off"
  }]
}
